pushoverkit/__init__.py
pushoverkit/__main__.py
pushoverkit/client.py
pushoverkit/groups.py
pushoverkit/teams.py
pushoverkit/cli/__init__.py
pushoverkit/cli/groups_cli.py
pushoverkit/cli/main.py
pushoverkit/cli/message_cli.py
pushoverkit/cli/teams_cli.py
pushoverkit-0.2.0.dist-info/licenses/LICENSE
pushoverkit-0.2.0.dist-info/METADATA
pushoverkit-0.2.0.dist-info/WHEEL
pushoverkit-0.2.0.dist-info/entry_points.txt
pushoverkit-0.2.0.dist-info/top_level.txt
pushoverkit-0.2.0.dist-info/RECORD
