Metadata-Version: 2.4
Name: pushoverkit
Version: 0.2.0
Summary: A powerful and Pythonic wrapper for the Pushover API with CLI support
Home-page: https://github.com/tranngocminhhieu/pushoverkit
Author: Trần Ngọc Minh Hiếu
Author-email: tnmhieu@gmail.com
License: MIT
Requires-Python: >=3.7
License-File: LICENSE
Requires-Dist: requests
Dynamic: author
Dynamic: author-email
Dynamic: description
Dynamic: description-content-type
Dynamic: home-page
Dynamic: license
Dynamic: license-file
Dynamic: requires-dist
Dynamic: requires-python
Dynamic: summary
